odoo/addons/hr_expense_cancel/README.rst
odoo/addons/hr_expense_cancel/__init__.py
odoo/addons/hr_expense_cancel/__manifest__.py
odoo/addons/hr_expense_cancel/i18n/es.po
odoo/addons/hr_expense_cancel/i18n/hr_expense_cancel.pot
odoo/addons/hr_expense_cancel/migrations/14.0.2.0.0/post-migration.py
odoo/addons/hr_expense_cancel/models/__init__.py
odoo/addons/hr_expense_cancel/models/hr_expense.py
odoo/addons/hr_expense_cancel/readme/CONTRIBUTORS.rst
odoo/addons/hr_expense_cancel/readme/DESCRIPTION.rst
odoo/addons/hr_expense_cancel/readme/INSTALL.rst
odoo/addons/hr_expense_cancel/readme/USAGE.rst
odoo/addons/hr_expense_cancel/static/description/icon.png
odoo/addons/hr_expense_cancel/static/description/index.html
odoo/addons/hr_expense_cancel/tests/__init__.py
odoo/addons/hr_expense_cancel/tests/test_hr_expense_cancel.py
odoo/addons/hr_expense_cancel/views/hr_expense_views.xml
odoo14_addon_hr_expense_cancel-14.0.2.0.1.dist-info/METADATA
odoo14_addon_hr_expense_cancel-14.0.2.0.1.dist-info/WHEEL
odoo14_addon_hr_expense_cancel-14.0.2.0.1.dist-info/top_level.txt
odoo14_addon_hr_expense_cancel-14.0.2.0.1.dist-info/RECORD
